<?xml version="1.0" encoding="UTF-8" standalone="no"?>
<teiHeader xmlns="http://www.tei-c.org/ns/1.0" xmlns:nkjp="http://www.nkjp.pl/ns/1.0" xml:lang="en">
  <fileDesc>
    <titleStmt>
      <title>Paragraphs: p-2581,p-2582,p-2583,p-2584,p-2585,p-2586,p-2587,p-2588,p-2589,p-2590,p-2591 from NKJP text with id: IJPPAN_2004000000062</title>
    </titleStmt>
  </fileDesc>
  <profileDesc>
    <textClass>
      <catRef scheme="#nkjp" target="Literatura piękna"/>
    </textClass>
  </profileDesc>
  <revisionDesc/>
</teiHeader>
